adv_math/__init__.py
adv_math/arithmetic.py
adv_math-0.0.3.dist-info/METADATA
adv_math-0.0.3.dist-info/WHEEL
adv_math-0.0.3.dist-info/top_level.txt
adv_math-0.0.3.dist-info/RECORD
