Metadata-Version: 2.1
Name: adv-math
Version: 0.0.3
Summary: Advanced Math
Home-page: UNKNOWN
Author: MrigKrafts
Author-email: <mrigkrafts@gmail.com>
License: UNKNOWN
Keywords: python,math
Platform: UNKNOWN
Classifier: Development Status :: 1 - Planning
Classifier: Intended Audience :: Developers
Classifier: Programming Language :: Python :: 3
Classifier: Operating System :: Unix
Classifier: Operating System :: MacOS :: MacOS X
Classifier: Operating System :: Microsoft :: Windows
